commonrdv/__init__.py
commonrdv/core/__init__.py
commonrdv/core/config.py
commonrdv/crud/__init__.py
commonrdv/crud/base.py
commonrdv/crud/crud_editor.py
commonrdv/crud/crud_token_ants_to_editor.py
commonrdv/crud/crud_token_editor_to_ants.py
commonrdv/db/__init__.py
commonrdv/db/postgresdb.py
commonrdv/db/postgresdb_utils.py
commonrdv/db/schemas.py
commonrdv/db/utils.py
commonrdv/logging/__init__.py
commonrdv/logging/app_logger.py
commonrdv/logging/app_logger_formatter.py
commonrdv/models/__init__.py
commonrdv/models/application.py
commonrdv/models/available_time_slot.py
commonrdv/models/editor.py
commonrdv/models/editor_model.py
commonrdv/models/municipality.py
commonrdv/models/token_ants_to_editor.py
commonrdv/models/token_editor_to_ants.py
commonrdv/schemas/__init__.py
commonrdv/schemas/editor.py
commonrdv/schemas/token_ants_to_editor.py
commonrdv/schemas/token_editor_to_ants.py
commonrdv/utils/__init__.py
commonrdv/utils/data_validator.py
commonrdv/utils/excel_helper.py
commonrdv-0.0.9b0.dist-info/LICENSE
commonrdv-0.0.9b0.dist-info/METADATA
commonrdv-0.0.9b0.dist-info/WHEEL
commonrdv-0.0.9b0.dist-info/top_level.txt
commonrdv-0.0.9b0.dist-info/RECORD
