Metadata-Version: 2.1
Name: commonrdv
Version: 0.0.9b0
Summary: Librairie commune pour les API de rendez-vous mairie
Author-email: WL <julien.dudek@worldline.com>
License: The MIT License (MIT)
Project-URL: documentation, https://rendez-vous-api.france-identite.fr/docs
Project-URL: repository, https://gitlab.com/france-identite/rendez-vous-mairie
Keywords: rendez-vous,mairie,proxy,pré-demande,passeport,CNI
Classifier: License :: OSI Approved :: MIT License
Classifier: Programming Language :: Python
Classifier: Programming Language :: Python :: 3
Requires-Python: >=3.10
License-File: LICENSE
Requires-Dist: asyncio ==3.4.3
Requires-Dist: fastapi ==0.100.0b2
Requires-Dist: fastapi-utils ==0.2.1
Requires-Dist: geopy ==2.3.0
Requires-Dist: pydantic ==1.10.12
Requires-Dist: python-dotenv ==1.0.0
Requires-Dist: slowapi ==0.1.8
Requires-Dist: uvicorn ==0.23.2
Requires-Dist: websockets ==11.0.3
Requires-Dist: pytest-mock ==3.11.1
Requires-Dist: secweb ==1.7.2
Requires-Dist: markdown ==3.4.4
Requires-Dist: unidecode ==1.3.6
Requires-Dist: httpx ==0.24.1
Requires-Dist: requests ==2.31.0
Requires-Dist: msoffcrypto-tool ==5.1.1
Requires-Dist: openpyxl ==3.1.2
Requires-Dist: python-dateutil ==2.8.2
Provides-Extra: dev
Requires-Dist: black ; extra == 'dev'
Requires-Dist: flake8 ; extra == 'dev'
Requires-Dist: isort ; extra == 'dev'
Requires-Dist: autoflake ; extra == 'dev'
Requires-Dist: bandit ; extra == 'dev'
Requires-Dist: pytest ; extra == 'dev'
Requires-Dist: pytest-asyncio ; extra == 'dev'
Requires-Dist: pytest-mock ; extra == 'dev'
Requires-Dist: pytest-cov ; extra == 'dev'
Requires-Dist: coverage ; extra == 'dev'
